iotile_support_lib_controller_4/__init__.py
iotile_support_lib_controller_4/configmanager.py
iotile_support_lib_controller_4/controllertest.py
iotile_support_lib_controller_4/firmware_image_analyzer.py
iotile_support_lib_controller_4/reference_controller_proxy.py
iotile_support_lib_controller_4/remotebridge.py
iotile_support_lib_controller_4/sensorgraph.py
iotile_support_lib_controller_4/tilemanager.py
iotile_support_lib_controller_4/data/pingpong_exec_bundle.hex
iotile_support_lib_controller_4/data/s112_nrf52_6.1.1_softdevice.hex
iotile_support_lib_controller_4/lib_controller_types/__init__.py
iotile_support_lib_controller_4/lib_controller_types/fw_configvariable.py
iotile_support_lib_controller_4/lib_controller_types/fw_graphnode.py
iotile_support_lib_controller_4/lib_controller_types/fw_reading.py
iotile_support_lib_controller_4/lib_controller_types/fw_stream.py
iotile_support_lib_controller_4/lib_controller_types/fw_streamerstatus.py
iotile_support_lib_controller_4/lib_controller_types/fw_tiledescriptor.py
iotile_support_lib_controller_4/lib_controller_types/fw_tileselector.py
iotile_support_lib_controller_4-4.3.6.dist-info/METADATA
iotile_support_lib_controller_4-4.3.6.dist-info/WHEEL
iotile_support_lib_controller_4-4.3.6.dist-info/entry_points.txt
iotile_support_lib_controller_4-4.3.6.dist-info/top_level.txt
iotile_support_lib_controller_4-4.3.6.dist-info/RECORD
